ogcFeatureApiCollectionDownloader/__init__.py
ogcFeatureApiCollectionDownloader/downloader.py
ogcFeatureApiCollectionDownloader-0.0.1.dist-info/LICENSE
ogcFeatureApiCollectionDownloader-0.0.1.dist-info/METADATA
ogcFeatureApiCollectionDownloader-0.0.1.dist-info/WHEEL
ogcFeatureApiCollectionDownloader-0.0.1.dist-info/entry_points.txt
ogcFeatureApiCollectionDownloader-0.0.1.dist-info/top_level.txt
ogcFeatureApiCollectionDownloader-0.0.1.dist-info/RECORD
