Metadata-Version: 2.1
Name: ogcFeatureApiCollectionDownloader
Version: 0.0.1
Summary: Automatically download a collection from an OGC Feature API
Home-page: https://github.com/mkeller3/ogcFeatureApiCollectionDownloader
Author: Michael Keller
Author-email: michaelkeller03@gmail.com
License: GNU General Public License v3.0
Platform: UNKNOWN
Classifier: License :: OSI Approved :: GNU General Public License v3 (GPLv3)
Classifier: Programming Language :: Python :: 3
Requires-Dist: requests (==2.28.1)
